Workbook
Name NPV: OFFSET(Calculation!$R$4,,,COUNTIF(Calculation!$R$4:$R$13,"<>"))
Name Saving: OFFSET(Calculation!$Q$4,,,COUNTIF(Calculation!$Q$4:$Q$13,"<>"))
Name Year: OFFSET(Calculation!$P$4,,,COUNTIF(Calculation!$P$4:$P$13,"<>"))

Sheet ROI and NPV analsyis
A3: Fill in the cells bordered in blue
A4: 1. Measure | C4: Metric | T4: NPV stands for net present value and is a discounts back the future cashflows(savings) to year 0 (=today). As assumptions we took an yearly growth rate of 1% and a WACC (interest rate) of 7,6%
A5: 2. Currency | C5: €
A6: Space | J6: Labour & Efficiency
A7: 3. Rack width | C7: 2.7 | D7: =IF($C$4="Metric",Input!B1,IF($C$4="Imperial",Input!B2,"")) -> m | J7: 8. Picks per hour / person | P7: 20 | T7: Annual Saving | V7: =C5 -> € | W7: =E29+P27 -> 19243.043
A8: 4. Rack depth | C8: 1 | D8: =IF($C$4="Metric",Input!$B$1,IF($C$4="Imperial",Input!$B$2,"")) -> m | J8: 9. # staff members | P8: 2 | T8: Net Present Value | V8: =C5 -> € | W8: =CHOOSE(G32,Calculation!C8,Calculation!D8,Calculation!E8,Calculation!F8,Calculation!G8,Calculation!H8,Calculation!I8,Calculation!J8,Calculation!K8,Calculation!L8) -> 15923.01
A9: =IF($C$4="Metric",Input!$C$1,IF($C$4="Imperial",Input!$C$2,"")) -> m² | C9: =C7*C8 -> 2.7 | J9: ="10. Wage staff member ("&C5&"/h)" -> 10. Wage staff member (€/h) | P9: 28 | T9: ROI | W9: =CHOOSE(G32,Calculation!C8,Calculation!D8,Calculation!E8,Calculation!F8,Calculation!G8,Calculation!H8,Calculation!I8,Calculation!J8,Calculation!K8,Calculation!L8)/G31 -> 0.45494315
T10: Payback term | W10: =G31/W7 -> 1.8188391 | X10: years
C11: Before/current | E11: When using SG
A12: 4. # Loc/rack | C12: 40 | E12: 90 | J12: 11. Efficiency Increase % | P12: 15 | Q12: %
A13: 5. # Racks | C13: 30 | E13: 15 | J13: 💡 Chalhoub had a 30% efficiency increase (click on the link to view)
A15: Total locations | C15: =C12*C13 -> 1200 | E15: =E12*E13 -> 1350 | N15: Before/current | P15: When using SG
A16: ="# Loc/"&A9 -> # Loc/m² | C16: =C12/C9 -> 14.814815 | E16: =E12/C9 -> 33.333333 | G16: =(E16-C16)/C16 -> 1.25 | J16: Annual picks * | N16: =P7*P8*8*0.8*260 -> 66560 | P16: =P7*P8*8*0.8*260 -> 66560
J17: Annual staff cost | M17: =C5 -> € | N17: =P8*260*8*P9 -> 116480 | O17: =C5 -> € | P17: =(P8/(P16*(1+(P12/100))))*N16*P9*8*260 -> 101286.96 | Q17: =(P17-N17)/N17 -> -0.13043478
A18: ="Walking distance in "&D8 -> Walking distance in m | C18: =C13*C7 -> 81 | E18: =E13*C7 -> 40.5 | G18: =(E18-C18)/C18 -> -0.5 | J18: Cost per pick | M18: =C5 -> € | N18: =N17/N16 -> 1.75 | O18: =C5 -> € | P18: =P17/P16 -> 1.5217391
A20: ="6. "&C5&"/"&A9&" (annual cost)" -> 6. €/m² (annual cost) | E20: 90
A21: ="7. Utility cost per "&A9&" (annual)" -> 7. Utility cost per m² (annual) | E21: 10
I22: * annual picks is calculated as picks per hour * # staff members * 8 working hours/day * 260 workingsdays a year at a 80% worktime spending
C23: Before/current | E23: When using SG
A24: Annual space cost | B24: =C5 -> € | C24: =C13*C9*E20 -> 7290 | E24: =E13*C9*E20 -> 3645
A25: Annual utility cost | B25: =C5 -> € | C25: =C13*C9*E21 -> 810 | E25: =E13*C9*E21 -> 405
A27: Annual space saving | D27: =C5 -> € | E27: =(C13-E13)*C9*E20 -> 3645 | J27: Annual labour saving | M27: =C5 -> € | P27: =N17-P17 -> 15193.043
A28: Annual utility saving | D28: =C5 -> € | E28: =(C13-E13)*C9*E21 -> 405
D29: =C5 -> € | E29: =SUM(E27:E28) -> 4050
A31: 12. Total Storeganizer investment | F31: =C5 -> € | G31: 35000
A32: 13. Investment horizon in years | G32: 3
A33: Additional comment section
S40: =E27 -> 3645

Sheet Calculation
A1: WACC | B1: 0.0761
A2: Inflation | B2: 0.01 | O2: ='ROI and NPV analsyis'!$G$32+2 -> 5 | P2: Year | Q2: Saving | R2: NPV
O3: 0
A4: Year | B4: 0 | C4: 1 | D4: 2 | E4: 3 | F4: 4 | G4: 5 | H4: 6 | I4: 7 | J4: 8 | K4: 9 | L4: 10 | O4: 1 | P4: =IF(O4<=$O$2,O4,"") -> 1 | Q4: =IF(P4<>"",C5,"") -> 19435.474 | R4: =IF(P4<>"",C8,"") -> -16938.97
A5: Saving | B5: =-'ROI and NPV analsyis'!G31 -> -35000 | C5: ='ROI and NPV analsyis'!$W$7*(1+$B$2)^C4 -> 19435.474 | D5: ='ROI and NPV analsyis'!$W$7*(1+$B$2)^D4 -> 19629.829 | E5: ='ROI and NPV analsyis'!$W$7*(1+$B$2)^E4 -> 19826.127 | F5: ='ROI and NPV analsyis'!$W$7*(1+$B$2)^F4 -> 20024.388 | G5: ='ROI and NPV analsyis'!$W$7*(1+$B$2)^G4 -> 20224.632 | H5: ='ROI and NPV analsyis'!$W$7*(1+$B$2)^H4 -> 20426.878 | I5: ='ROI and NPV analsyis'!$W$7*(1+$B$2)^I4 -> 20631.147 | J5: ='ROI and NPV analsyis'!$W$7*(1+$B$2)^J4 -> 20837.459 | ... L5: ='ROI and NPV analsyis'!$W$7*(1+$B$2)^L4 -> 21256.292 | O5: 2 | P5: =IF(O5<=$O$2,O5,"") -> 2 | Q5: =IF(P5<>"",D5,"") -> 19629.829 | R5: =IF(P5<>"",D8,"") -> 12.651029
A6: Discounted to year 0 | B6: =B5 -> -35000 | C6: =C5/((1+$B$1)^C4) -> 18061.03 | D6: =D5/((1+$B$1)^D4) -> 16951.621 | E6: =E5/((1+$B$1)^E4) -> 15910.359 | F6: =F5/((1+$B$1)^F4) -> 14933.057 | G6: =G5/((1+$B$1)^G4) -> 14015.786 | H6: =H5/((1+$B$1)^H4) -> 13154.86 | I6: =I5/((1+$B$1)^I4) -> 12346.815 | J6: =J5/((1+$B$1)^J4) -> 11588.406 | ... L6: =L5/((1+$B$1)^L4) -> 10208.482 | O6: 3 | P6: =IF(O6<=$O$2,O6,"") -> 3 | Q6: =IF(P6<>"",E5,"") -> 19826.127 | R6: =IF(P6<>"",E8,"") -> 15923.01
A7: Cumulative cashfflow | B7: =B6 -> -35000 | C7: =SUM($B6:C6) -> -16938.97 | D7: =SUM($B6:D6) -> 12.651029 | E7: =SUM($B6:E6) -> 15923.01 | F7: =SUM($B6:F6) -> 30856.068 | G7: =SUM($B6:G6) -> 44871.854 | H7: =SUM($B6:H6) -> 58026.714 | I7: =SUM($B6:I6) -> 70373.529 | J7: =SUM($B6:J6) -> 81961.935 | ... L7: =SUM($B6:L6) -> 103047 | O7: 4 | P7: =IF(O7<=$O$2,O7,"") -> 4 | Q7: =IF(P7<>"",F5,"") -> 20024.388 | R7: =IF(P7<>"",F8,"") -> 30856.068
A8: NPV | C8: =NPV($B$1,$C$5:C5)+$B$5 -> -16938.97 | D8: =NPV($B$1,$C$5:D5)+$B$5 -> 12.651029 | E8: =NPV($B$1,$C$5:E5)+$B$5 -> 15923.01 | F8: =NPV($B$1,$C$5:F5)+$B$5 -> 30856.068 | G8: =NPV($B$1,$C$5:G5)+$B$5 -> 44871.854 | H8: =NPV($B$1,$C$5:H5)+$B$5 -> 58026.714 | I8: =NPV($B$1,$C$5:I5)+$B$5 -> 70373.529 | J8: =NPV($B$1,$C$5:J5)+$B$5 -> 81961.935 | ... L8: =NPV($B$1,$C$5:L5)+$B$5 -> 103047 | O8: 5 | P8: =IF(O8<=$O$2,O8,"") -> 5 | Q8: =IF(P8<>"",G5,"") -> 20224.632 | R8: =IF(P8<>"",G8,"") -> 44871.854
O9: 6 | P9: =IF(O9<=$O$2,O9,"") | Q9: =IF(P9<>"",H5,"") | R9: =IF(P9<>"",H8,"")
O10: 7 | P10: =IF(O10<=$O$2,O10,"") | Q10: =IF(P10<>"",I5,"") | R10: =IF(P10<>"",I8,"")
A11: Yearly amoriztation | B11: =CHOOSE('ROI and NPV analsyis'!G32,Calculation!C11,Calculation!D11,Calculation!E11,Calculation!F11,Calculation!G11,Calculation!H11,Calculation!I11,Calculation!J11,Calculation!K11,Calculation!L11) -> 11666.667 | C11: ='ROI and NPV analsyis'!$G$31/Calculation!C4 -> 35000 | D11: ='ROI and NPV analsyis'!$G$31/Calculation!D4 -> 17500 | E11: ='ROI and NPV analsyis'!$G$31/Calculation!E4 -> 11666.667 | F11: ='ROI and NPV analsyis'!$G$31/Calculation!F4 -> 8750 | G11: ='ROI and NPV analsyis'!$G$31/Calculation!G4 -> 7000 | H11: ='ROI and NPV analsyis'!$G$31/Calculation!H4 -> 5833.3333 | I11: ='ROI and NPV analsyis'!$G$31/Calculation!I4 -> 5000 | J11: ='ROI and NPV analsyis'!$G$31/Calculation!J4 -> 4375 | ... L11: ='ROI and NPV analsyis'!$G$31/Calculation!L4 -> 3500 | O11: 8 | P11: =IF(O11<=$O$2,O11,"") | Q11: =IF(P11<>"",J5,"") | R11: =IF(P11<>"",J8,"")
A12: Investment | B12: =C11 -> 35000 | O12: 9 | P12: =IF(O12<=$O$2,O12,"") | Q12: =IF(P12<>"",K5,"") | R12: =IF(P12<>"",K8,"")
A13: Outstanding value | C13: =B12-$B$11 -> 23333.333 | D13: =C13-$B$11 -> 11666.667 | E13: =D13-$B$11 -> 0 | F13: =E13-$B$11 -> -11666.667 | G13: =F13-$B$11 -> -23333.333 | H13: =G13-$B$11 -> -35000 | I13: =H13-$B$11 -> -46666.667 | J13: =I13-$B$11 -> -58333.333 | K13: =J13-$B$11 -> -70000 | L13: =K13-$B$11 -> -81666.667 | O13: 10 | P13: =IF(O13<=$O$2,O13,"") | Q13: =IF(P13<>"",L5,"") | R13: =IF(P13<>"",L8,"")
A14: Amortization | C14: =IF(C13>=0,$B$11,0) -> 11666.667 | D14: =IF(D13>=0,$B$11,0) -> 11666.667 | E14: =IF(E13>=0,$B$11,0) -> 11666.667 | F14: =IF(F13>=0,$B$11,0) -> 0 | G14: =IF(G13>=0,$B$11,0) -> 0 | H14: =IF(H13>=0,$B$11,0) -> 0 | I14: =IF(I13>=0,$B$11,0) -> 0 | J14: =IF(J13>=0,$B$11,0) -> 0 | ... L14: =IF(L13>=0,$B$11,0) -> 0
B20: 0 | C20: 1 | D20: 2 | E20: 3 | F20: 4 | G20: 5 | H20: 6 | I20: 7 | J20: 8 | K20: 9 | L20: 10
A21: 0 | C21: =('ROI and NPV analsyis'!$N$17-(('ROI and NPV analsyis'!$P$8/('ROI and NPV analsyis'!$P$16*(1+$A21)))*'ROI and NPV analsyis'!$N$16*'ROI and NPV analsyis'!$P$9*8*260))+'ROI and NPV analsyis'!$E$29*(1+$B$2)^C$4 -> 4090.5 | D21: =('ROI and NPV analsyis'!$N$17-(('ROI and NPV analsyis'!$P$8/('ROI and NPV analsyis'!$P$16*(1+$A21)))*'ROI and NPV analsyis'!$N$16*'ROI and NPV analsyis'!$P$9*8*260))+'ROI and NPV analsyis'!$E$29*(1+$B$2)^D$4 -> 4131.405 | E21: =('ROI and NPV analsyis'!$N$17-(('ROI and NPV analsyis'!$P$8/('ROI and NPV analsyis'!$P$16*(1+$A21)))*'ROI and NPV analsyis'!$N$16*'ROI and NPV analsyis'!$P$9*8*260))+'ROI and NPV analsyis'!$E$29*(1+$B$2)^E$4 -> 4172.719 | F21: =('ROI and NPV analsyis'!$N$17-(('ROI and NPV analsyis'!$P$8/('ROI and NPV analsyis'!$P$16*(1+$A21)))*'ROI and NPV analsyis'!$N$16*'ROI and NPV analsyis'!$P$9*8*260))+'ROI and NPV analsyis'!$E$29*(1+$B$2)^F$4 -> 4214.4462 | G21: =('ROI and NPV analsyis'!$N$17-(('ROI and NPV analsyis'!$P$8/('ROI and NPV analsyis'!$P$16*(1+$A21)))*'ROI and NPV analsyis'!$N$16*'ROI and NPV analsyis'!$P$9*8*260))+'ROI and NPV analsyis'!$E$29*(1+$B$2)^G$4 -> 4256.5907 | H21: =('ROI and NPV analsyis'!$N$17-(('ROI and NPV analsyis'!$P$8/('ROI and NPV analsyis'!$P$16*(1+$A21)))*'ROI and NPV analsyis'!$N$16*'ROI and NPV analsyis'!$P$9*8*260))+'ROI and NPV analsyis'!$E$29*(1+$B$2)^H$4 -> 4299.1566 | I21: =('ROI and NPV analsyis'!$N$17-(('ROI and NPV analsyis'!$P$8/('ROI and NPV analsyis'!$P$16*(1+$A21)))*'ROI and NPV analsyis'!$N$16*'ROI and NPV analsyis'!$P$9*8*260))+'ROI and NPV analsyis'!$E$29*(1+$B$2)^I$4 -> 4342.1482 | J21: =('ROI and NPV analsyis'!$N$17-(('ROI and NPV analsyis'!$P$8/('ROI and NPV analsyis'!$P$16*(1+$A21)))*'ROI and NPV analsyis'!$N$16*'ROI and NPV analsyis'!$P$9*8*260))+'ROI and NPV analsyis'!$E$29*(1+$B$2)^J$4 -> 4385.5697 | ... L21: =('ROI and NPV analsyis'!$N$17-(('ROI and NPV analsyis'!$P$8/('ROI and NPV analsyis'!$P$16*(1+$A21)))*'ROI and NPV analsyis'!$N$16*'ROI and NPV analsyis'!$P$9*8*260))+'ROI and NPV analsyis'!$E$29*(1+$B$2)^L$4 -> 4473.7196
A22: 0 | C22: =NPV($B$1,$C$21:C21)-$B$12 -> -31198.773 | D22: =NPV($B$1,$C$21:D21)-$B$12 -> -27631.039 | E22: =NPV($B$1,$C$21:E21)-$B$12 -> -24282.455 | F22: =NPV($B$1,$C$21:F21)-$B$12 -> -21139.559 | G22: =NPV($B$1,$C$21:G21)-$B$12 -> -18189.717 | H22: =NPV($B$1,$C$21:H21)-$B$12 -> -15421.071 | I22: =NPV($B$1,$C$21:I21)-$B$12 -> -12822.49 | J22: =NPV($B$1,$C$21:J21)-$B$12 -> -10383.528 | ... L22: =NPV($B$1,$C$21:L21)-$B$12 -> -5945.846
A23: 0.05 | C23: =('ROI and NPV analsyis'!$N$17-(('ROI and NPV analsyis'!$P$8/('ROI and NPV analsyis'!$P$16*(1+$A23)))*'ROI and NPV analsyis'!$N$16*'ROI and NPV analsyis'!$P$9*8*260))+'ROI and NPV analsyis'!$E$29*(1+$B$2)^C$4 -> 9637.1667 | D23: =('ROI and NPV analsyis'!$N$17-(('ROI and NPV analsyis'!$P$8/('ROI and NPV analsyis'!$P$16*(1+$A23)))*'ROI and NPV analsyis'!$N$16*'ROI and NPV analsyis'!$P$9*8*260))+'ROI and NPV analsyis'!$E$29*(1+$B$2)^D$4 -> 9678.0717 | E23: =('ROI and NPV analsyis'!$N$17-(('ROI and NPV analsyis'!$P$8/('ROI and NPV analsyis'!$P$16*(1+$A23)))*'ROI and NPV analsyis'!$N$16*'ROI and NPV analsyis'!$P$9*8*260))+'ROI and NPV analsyis'!$E$29*(1+$B$2)^E$4 -> 9719.3857 | F23: =('ROI and NPV analsyis'!$N$17-(('ROI and NPV analsyis'!$P$8/('ROI and NPV analsyis'!$P$16*(1+$A23)))*'ROI and NPV analsyis'!$N$16*'ROI and NPV analsyis'!$P$9*8*260))+'ROI and NPV analsyis'!$E$29*(1+$B$2)^F$4 -> 9761.1129 | G23: =('ROI and NPV analsyis'!$N$17-(('ROI and NPV analsyis'!$P$8/('ROI and NPV analsyis'!$P$16*(1+$A23)))*'ROI and NPV analsyis'!$N$16*'ROI and NPV analsyis'!$P$9*8*260))+'ROI and NPV analsyis'!$E$29*(1+$B$2)^G$4 -> 9803.2574 | H23: =('ROI and NPV analsyis'!$N$17-(('ROI and NPV analsyis'!$P$8/('ROI and NPV analsyis'!$P$16*(1+$A23)))*'ROI and NPV analsyis'!$N$16*'ROI and NPV analsyis'!$P$9*8*260))+'ROI and NPV analsyis'!$E$29*(1+$B$2)^H$4 -> 9845.8233 | I23: =('ROI and NPV analsyis'!$N$17-(('ROI and NPV analsyis'!$P$8/('ROI and NPV analsyis'!$P$16*(1+$A23)))*'ROI and NPV analsyis'!$N$16*'ROI and NPV analsyis'!$P$9*8*260))+'ROI and NPV analsyis'!$E$29*(1+$B$2)^I$4 -> 9888.8148 | J23: =('ROI and NPV analsyis'!$N$17-(('ROI and NPV analsyis'!$P$8/('ROI and NPV analsyis'!$P$16*(1+$A23)))*'ROI and NPV analsyis'!$N$16*'ROI and NPV analsyis'!$P$9*8*260))+'ROI and NPV analsyis'!$E$29*(1+$B$2)^J$4 -> 9932.2363 | ... L23: =('ROI and NPV analsyis'!$N$17-(('ROI and NPV analsyis'!$P$8/('ROI and NPV analsyis'!$P$16*(1+$A23)))*'ROI and NPV analsyis'!$N$16*'ROI and NPV analsyis'!$P$9*8*260))+'ROI and NPV analsyis'!$E$29*(1+$B$2)^L$4 -> 10020.386
A24: 0.05 | C24: =NPV($B$1,$C$23:C23)-$B$12 -> -26044.358 | D24: =NPV($B$1,$C$23:D23)-$B$12 -> -17686.719 | E24: =NPV($B$1,$C$23:E23)-$B$12 -> -9886.9651 | F24: =NPV($B$1,$C$23:F23)-$B$12 -> -2607.6786 | G24: =NPV($B$1,$C$23:G23)-$B$12 -> 4186.0352 | H24: =NPV($B$1,$C$23:H23)-$B$12 -> 10526.721 | I24: =NPV($B$1,$C$23:I23)-$B$12 -> 16444.733 | J24: =NPV($B$1,$C$23:J23)-$B$12 -> 21968.381 | ... L24: =NPV($B$1,$C$23:L23)-$B$12 -> 31936.431
A25: 0.1 | C25: =('ROI and NPV analsyis'!$N$17-(('ROI and NPV analsyis'!$P$8/('ROI and NPV analsyis'!$P$16*(1+$A25)))*'ROI and NPV analsyis'!$N$16*'ROI and NPV analsyis'!$P$9*8*260))+'ROI and NPV analsyis'!$E$29*(1+$B$2)^C$4 -> 14679.591 | D25: =('ROI and NPV analsyis'!$N$17-(('ROI and NPV analsyis'!$P$8/('ROI and NPV analsyis'!$P$16*(1+$A25)))*'ROI and NPV analsyis'!$N$16*'ROI and NPV analsyis'!$P$9*8*260))+'ROI and NPV analsyis'!$E$29*(1+$B$2)^D$4 -> 14720.496 | E25: =('ROI and NPV analsyis'!$N$17-(('ROI and NPV analsyis'!$P$8/('ROI and NPV analsyis'!$P$16*(1+$A25)))*'ROI and NPV analsyis'!$N$16*'ROI and NPV analsyis'!$P$9*8*260))+'ROI and NPV analsyis'!$E$29*(1+$B$2)^E$4 -> 14761.81 | F25: =('ROI and NPV analsyis'!$N$17-(('ROI and NPV analsyis'!$P$8/('ROI and NPV analsyis'!$P$16*(1+$A25)))*'ROI and NPV analsyis'!$N$16*'ROI and NPV analsyis'!$P$9*8*260))+'ROI and NPV analsyis'!$E$29*(1+$B$2)^F$4 -> 14803.537 | G25: =('ROI and NPV analsyis'!$N$17-(('ROI and NPV analsyis'!$P$8/('ROI and NPV analsyis'!$P$16*(1+$A25)))*'ROI and NPV analsyis'!$N$16*'ROI and NPV analsyis'!$P$9*8*260))+'ROI and NPV analsyis'!$E$29*(1+$B$2)^G$4 -> 14845.682 | H25: =('ROI and NPV analsyis'!$N$17-(('ROI and NPV analsyis'!$P$8/('ROI and NPV analsyis'!$P$16*(1+$A25)))*'ROI and NPV analsyis'!$N$16*'ROI and NPV analsyis'!$P$9*8*260))+'ROI and NPV analsyis'!$E$29*(1+$B$2)^H$4 -> 14888.248 | I25: =('ROI and NPV analsyis'!$N$17-(('ROI and NPV analsyis'!$P$8/('ROI and NPV analsyis'!$P$16*(1+$A25)))*'ROI and NPV analsyis'!$N$16*'ROI and NPV analsyis'!$P$9*8*260))+'ROI and NPV analsyis'!$E$29*(1+$B$2)^I$4 -> 14931.239 | J25: =('ROI and NPV analsyis'!$N$17-(('ROI and NPV analsyis'!$P$8/('ROI and NPV analsyis'!$P$16*(1+$A25)))*'ROI and NPV analsyis'!$N$16*'ROI and NPV analsyis'!$P$9*8*260))+'ROI and NPV analsyis'!$E$29*(1+$B$2)^J$4 -> 14974.661 | ... L25: =('ROI and NPV analsyis'!$N$17-(('ROI and NPV analsyis'!$P$8/('ROI and NPV analsyis'!$P$16*(1+$A25)))*'ROI and NPV analsyis'!$N$16*'ROI and NPV analsyis'!$P$9*8*260))+'ROI and NPV analsyis'!$E$29*(1+$B$2)^L$4 -> 15062.811
A26: 0.1 | C26: =NPV($B$1,$C$25:C25)-$B$12 -> -21358.525 | D26: =NPV($B$1,$C$25:D25)-$B$12 -> -8646.4289 | E26: =NPV($B$1,$C$25:E25)-$B$12 -> 3199.8435 | F26: =NPV($B$1,$C$25:F25)-$B$12 -> 14239.485 | G26: =NPV($B$1,$C$25:G25)-$B$12 -> 24527.628 | H26: =NPV($B$1,$C$25:H25)-$B$12 -> 34115.623 | I26: =NPV($B$1,$C$25:I25)-$B$12 -> 43051.299 | J26: =NPV($B$1,$C$25:J25)-$B$12 -> 51379.207 | ... L26: =NPV($B$1,$C$25:L25)-$B$12 -> 66374.865
A27: 0.15 | C27: =('ROI and NPV analsyis'!$N$17-(('ROI and NPV analsyis'!$P$8/('ROI and NPV analsyis'!$P$16*(1+$A27)))*'ROI and NPV analsyis'!$N$16*'ROI and NPV analsyis'!$P$9*8*260))+'ROI and NPV analsyis'!$E$29*(1+$B$2)^C$4 -> 19283.543 | D27: =('ROI and NPV analsyis'!$N$17-(('ROI and NPV analsyis'!$P$8/('ROI and NPV analsyis'!$P$16*(1+$A27)))*'ROI and NPV analsyis'!$N$16*'ROI and NPV analsyis'!$P$9*8*260))+'ROI and NPV analsyis'!$E$29*(1+$B$2)^D$4 -> 19324.448 | E27: =('ROI and NPV analsyis'!$N$17-(('ROI and NPV analsyis'!$P$8/('ROI and NPV analsyis'!$P$16*(1+$A27)))*'ROI and NPV analsyis'!$N$16*'ROI and NPV analsyis'!$P$9*8*260))+'ROI and NPV analsyis'!$E$29*(1+$B$2)^E$4 -> 19365.763 | F27: =('ROI and NPV analsyis'!$N$17-(('ROI and NPV analsyis'!$P$8/('ROI and NPV analsyis'!$P$16*(1+$A27)))*'ROI and NPV analsyis'!$N$16*'ROI and NPV analsyis'!$P$9*8*260))+'ROI and NPV analsyis'!$E$29*(1+$B$2)^F$4 -> 19407.49 | G27: =('ROI and NPV analsyis'!$N$17-(('ROI and NPV analsyis'!$P$8/('ROI and NPV analsyis'!$P$16*(1+$A27)))*'ROI and NPV analsyis'!$N$16*'ROI and NPV analsyis'!$P$9*8*260))+'ROI and NPV analsyis'!$E$29*(1+$B$2)^G$4 -> 19449.634 | H27: =('ROI and NPV analsyis'!$N$17-(('ROI and NPV analsyis'!$P$8/('ROI and NPV analsyis'!$P$16*(1+$A27)))*'ROI and NPV analsyis'!$N$16*'ROI and NPV analsyis'!$P$9*8*260))+'ROI and NPV analsyis'!$E$29*(1+$B$2)^H$4 -> 19492.2 | I27: =('ROI and NPV analsyis'!$N$17-(('ROI and NPV analsyis'!$P$8/('ROI and NPV analsyis'!$P$16*(1+$A27)))*'ROI and NPV analsyis'!$N$16*'ROI and NPV analsyis'!$P$9*8*260))+'ROI and NPV analsyis'!$E$29*(1+$B$2)^I$4 -> 19535.192 | J27: =('ROI and NPV analsyis'!$N$17-(('ROI and NPV analsyis'!$P$8/('ROI and NPV analsyis'!$P$16*(1+$A27)))*'ROI and NPV analsyis'!$N$16*'ROI and NPV analsyis'!$P$9*8*260))+'ROI and NPV analsyis'!$E$29*(1+$B$2)^J$4 -> 19578.613 | ... L27: =('ROI and NPV analsyis'!$N$17-(('ROI and NPV analsyis'!$P$8/('ROI and NPV analsyis'!$P$16*(1+$A27)))*'ROI and NPV analsyis'!$N$16*'ROI and NPV analsyis'!$P$9*8*260))+'ROI and NPV analsyis'!$E$29*(1+$B$2)^L$4 -> 19666.763
A28: 0.15 | C28: =NPV($B$1,$C$27:C27)-$B$12 -> -17080.157 | D28: =NPV($B$1,$C$27:D27)-$B$12 -> -392.25059 | E28: =NPV($B$1,$C$27:E27)-$B$12 -> 15148.669 | F28: =NPV($B$1,$C$27:F27)-$B$12 -> 29621.678 | G28: =NPV($B$1,$C$27:G27)-$B$12 -> 43100.387 | H28: =NPV($B$1,$C$27:H27)-$B$12 -> 55653.316 | I28: =NPV($B$1,$C$27:I27)-$B$12 -> 67344.251 | J28: =NPV($B$1,$C$27:J27)-$B$12 -> 78232.571 | ... L28: =NPV($B$1,$C$27:L27)-$B$12 -> 97818.652
A29: 0.2 | C29: =('ROI and NPV analsyis'!$N$17-(('ROI and NPV analsyis'!$P$8/('ROI and NPV analsyis'!$P$16*(1+$A29)))*'ROI and NPV analsyis'!$N$16*'ROI and NPV analsyis'!$P$9*8*260))+'ROI and NPV analsyis'!$E$29*(1+$B$2)^C$4 -> 23503.833 | D29: =('ROI and NPV analsyis'!$N$17-(('ROI and NPV analsyis'!$P$8/('ROI and NPV analsyis'!$P$16*(1+$A29)))*'ROI and NPV analsyis'!$N$16*'ROI and NPV analsyis'!$P$9*8*260))+'ROI and NPV analsyis'!$E$29*(1+$B$2)^D$4 -> 23544.738 | E29: =('ROI and NPV analsyis'!$N$17-(('ROI and NPV analsyis'!$P$8/('ROI and NPV analsyis'!$P$16*(1+$A29)))*'ROI and NPV analsyis'!$N$16*'ROI and NPV analsyis'!$P$9*8*260))+'ROI and NPV analsyis'!$E$29*(1+$B$2)^E$4 -> 23586.052 | F29: =('ROI and NPV analsyis'!$N$17-(('ROI and NPV analsyis'!$P$8/('ROI and NPV analsyis'!$P$16*(1+$A29)))*'ROI and NPV analsyis'!$N$16*'ROI and NPV analsyis'!$P$9*8*260))+'ROI and NPV analsyis'!$E$29*(1+$B$2)^F$4 -> 23627.78 | G29: =('ROI and NPV analsyis'!$N$17-(('ROI and NPV analsyis'!$P$8/('ROI and NPV analsyis'!$P$16*(1+$A29)))*'ROI and NPV analsyis'!$N$16*'ROI and NPV analsyis'!$P$9*8*260))+'ROI and NPV analsyis'!$E$29*(1+$B$2)^G$4 -> 23669.924 | H29: =('ROI and NPV analsyis'!$N$17-(('ROI and NPV analsyis'!$P$8/('ROI and NPV analsyis'!$P$16*(1+$A29)))*'ROI and NPV analsyis'!$N$16*'ROI and NPV analsyis'!$P$9*8*260))+'ROI and NPV analsyis'!$E$29*(1+$B$2)^H$4 -> 23712.49 | I29: =('ROI and NPV analsyis'!$N$17-(('ROI and NPV analsyis'!$P$8/('ROI and NPV analsyis'!$P$16*(1+$A29)))*'ROI and NPV analsyis'!$N$16*'ROI and NPV analsyis'!$P$9*8*260))+'ROI and NPV analsyis'!$E$29*(1+$B$2)^I$4 -> 23755.482 | J29: =('ROI and NPV analsyis'!$N$17-(('ROI and NPV analsyis'!$P$8/('ROI and NPV analsyis'!$P$16*(1+$A29)))*'ROI and NPV analsyis'!$N$16*'ROI and NPV analsyis'!$P$9*8*260))+'ROI and NPV analsyis'!$E$29*(1+$B$2)^J$4 -> 23798.903 | ... L29: =('ROI and NPV analsyis'!$N$17-(('ROI and NPV analsyis'!$P$8/('ROI and NPV analsyis'!$P$16*(1+$A29)))*'ROI and NPV analsyis'!$N$16*'ROI and NPV analsyis'!$P$9*8*260))+'ROI and NPV analsyis'!$E$29*(1+$B$2)^L$4 -> 23887.053
A30: 0.2 | C30: =NPV($B$1,$C$29:C29)-$B$12 -> -13158.319 | D30: =NPV($B$1,$C$29:D29)-$B$12 -> 7174.0795 | E30: =NPV($B$1,$C$29:E29)-$B$12 -> 26101.759 | F30: =NPV($B$1,$C$29:F29)-$B$12 -> 43722.022 | G30: =NPV($B$1,$C$29:G29)-$B$12 -> 60125.415 | H30: =NPV($B$1,$C$29:H29)-$B$12 -> 75396.201 | I30: =NPV($B$1,$C$29:I29)-$B$12 -> 89612.79 | J30: =NPV($B$1,$C$29:J29)-$B$12 -> 102848.15 | ... L30: =NPV($B$1,$C$29:L29)-$B$12 -> 126642.12
A31: 0.25 | C31: =('ROI and NPV analsyis'!$N$17-(('ROI and NPV analsyis'!$P$8/('ROI and NPV analsyis'!$P$16*(1+$A31)))*'ROI and NPV analsyis'!$N$16*'ROI and NPV analsyis'!$P$9*8*260))+'ROI and NPV analsyis'!$E$29*(1+$B$2)^C$4 -> 27386.5 | D31: =('ROI and NPV analsyis'!$N$17-(('ROI and NPV analsyis'!$P$8/('ROI and NPV analsyis'!$P$16*(1+$A31)))*'ROI and NPV analsyis'!$N$16*'ROI and NPV analsyis'!$P$9*8*260))+'ROI and NPV analsyis'!$E$29*(1+$B$2)^D$4 -> 27427.405 | E31: =('ROI and NPV analsyis'!$N$17-(('ROI and NPV analsyis'!$P$8/('ROI and NPV analsyis'!$P$16*(1+$A31)))*'ROI and NPV analsyis'!$N$16*'ROI and NPV analsyis'!$P$9*8*260))+'ROI and NPV analsyis'!$E$29*(1+$B$2)^E$4 -> 27468.719 | F31: =('ROI and NPV analsyis'!$N$17-(('ROI and NPV analsyis'!$P$8/('ROI and NPV analsyis'!$P$16*(1+$A31)))*'ROI and NPV analsyis'!$N$16*'ROI and NPV analsyis'!$P$9*8*260))+'ROI and NPV analsyis'!$E$29*(1+$B$2)^F$4 -> 27510.446 | G31: =('ROI and NPV analsyis'!$N$17-(('ROI and NPV analsyis'!$P$8/('ROI and NPV analsyis'!$P$16*(1+$A31)))*'ROI and NPV analsyis'!$N$16*'ROI and NPV analsyis'!$P$9*8*260))+'ROI and NPV analsyis'!$E$29*(1+$B$2)^G$4 -> 27552.591 | H31: =('ROI and NPV analsyis'!$N$17-(('ROI and NPV analsyis'!$P$8/('ROI and NPV analsyis'!$P$16*(1+$A31)))*'ROI and NPV analsyis'!$N$16*'ROI and NPV analsyis'!$P$9*8*260))+'ROI and NPV analsyis'!$E$29*(1+$B$2)^H$4 -> 27595.157 | I31: =('ROI and NPV analsyis'!$N$17-(('ROI and NPV analsyis'!$P$8/('ROI and NPV analsyis'!$P$16*(1+$A31)))*'ROI and NPV analsyis'!$N$16*'ROI and NPV analsyis'!$P$9*8*260))+'ROI and NPV analsyis'!$E$29*(1+$B$2)^I$4 -> 27638.148 | J31: =('ROI and NPV analsyis'!$N$17-(('ROI and NPV analsyis'!$P$8/('ROI and NPV analsyis'!$P$16*(1+$A31)))*'ROI and NPV analsyis'!$N$16*'ROI and NPV analsyis'!$P$9*8*260))+'ROI and NPV analsyis'!$E$29*(1+$B$2)^J$4 -> 27681.57 | ... L31: =('ROI and NPV analsyis'!$N$17-(('ROI and NPV analsyis'!$P$8/('ROI and NPV analsyis'!$P$16*(1+$A31)))*'ROI and NPV analsyis'!$N$16*'ROI and NPV analsyis'!$P$9*8*260))+'ROI and NPV analsyis'!$E$29*(1+$B$2)^L$4 -> 27769.72
A32: 0.25 | C32: =NPV($B$1,$C$31:C31)-$B$12 -> -9550.2277 | D32: =NPV($B$1,$C$31:D31)-$B$12 -> 14135.103 | E32: =NPV($B$1,$C$31:E31)-$B$12 -> 36178.601 | F32: =NPV($B$1,$C$31:F31)-$B$12 -> 56694.338 | G32: =NPV($B$1,$C$31:G31)-$B$12 -> 75788.442 | H32: =NPV($B$1,$C$31:H31)-$B$12 -> 93559.655 | I32: =NPV($B$1,$C$31:I31)-$B$12 -> 110099.85 | J32: =NPV($B$1,$C$31:J31)-$B$12 -> 125494.49 | ... L32: =NPV($B$1,$C$31:L31)-$B$12 -> 153159.72
A33: 0.3 | C33: =('ROI and NPV analsyis'!$N$17-(('ROI and NPV analsyis'!$P$8/('ROI and NPV analsyis'!$P$16*(1+$A33)))*'ROI and NPV analsyis'!$N$16*'ROI and NPV analsyis'!$P$9*8*260))+'ROI and NPV analsyis'!$E$29*(1+$B$2)^C$4 -> 30970.5 | D33: =('ROI and NPV analsyis'!$N$17-(('ROI and NPV analsyis'!$P$8/('ROI and NPV analsyis'!$P$16*(1+$A33)))*'ROI and NPV analsyis'!$N$16*'ROI and NPV analsyis'!$P$9*8*260))+'ROI and NPV analsyis'!$E$29*(1+$B$2)^D$4 -> 31011.405 | E33: =('ROI and NPV analsyis'!$N$17-(('ROI and NPV analsyis'!$P$8/('ROI and NPV analsyis'!$P$16*(1+$A33)))*'ROI and NPV analsyis'!$N$16*'ROI and NPV analsyis'!$P$9*8*260))+'ROI and NPV analsyis'!$E$29*(1+$B$2)^E$4 -> 31052.719 | F33: =('ROI and NPV analsyis'!$N$17-(('ROI and NPV analsyis'!$P$8/('ROI and NPV analsyis'!$P$16*(1+$A33)))*'ROI and NPV analsyis'!$N$16*'ROI and NPV analsyis'!$P$9*8*260))+'ROI and NPV analsyis'!$E$29*(1+$B$2)^F$4 -> 31094.446 | G33: =('ROI and NPV analsyis'!$N$17-(('ROI and NPV analsyis'!$P$8/('ROI and NPV analsyis'!$P$16*(1+$A33)))*'ROI and NPV analsyis'!$N$16*'ROI and NPV analsyis'!$P$9*8*260))+'ROI and NPV analsyis'!$E$29*(1+$B$2)^G$4 -> 31136.591 | H33: =('ROI and NPV analsyis'!$N$17-(('ROI and NPV analsyis'!$P$8/('ROI and NPV analsyis'!$P$16*(1+$A33)))*'ROI and NPV analsyis'!$N$16*'ROI and NPV analsyis'!$P$9*8*260))+'ROI and NPV analsyis'!$E$29*(1+$B$2)^H$4 -> 31179.157 | I33: =('ROI and NPV analsyis'!$N$17-(('ROI and NPV analsyis'!$P$8/('ROI and NPV analsyis'!$P$16*(1+$A33)))*'ROI and NPV analsyis'!$N$16*'ROI and NPV analsyis'!$P$9*8*260))+'ROI and NPV analsyis'!$E$29*(1+$B$2)^I$4 -> 31222.148 | J33: =('ROI and NPV analsyis'!$N$17-(('ROI and NPV analsyis'!$P$8/('ROI and NPV analsyis'!$P$16*(1+$A33)))*'ROI and NPV analsyis'!$N$16*'ROI and NPV analsyis'!$P$9*8*260))+'ROI and NPV analsyis'!$E$29*(1+$B$2)^J$4 -> 31265.57 | ... L33: =('ROI and NPV analsyis'!$N$17-(('ROI and NPV analsyis'!$P$8/('ROI and NPV analsyis'!$P$16*(1+$A33)))*'ROI and NPV analsyis'!$N$16*'ROI and NPV analsyis'!$P$9*8*260))+'ROI and NPV analsyis'!$E$29*(1+$B$2)^L$4 -> 31353.72
A34: 0.3 | C34: =NPV($B$1,$C$33:C33)-$B$12 -> -6219.6822 | D34: =NPV($B$1,$C$33:D33)-$B$12 -> 20560.664 | E34: =NPV($B$1,$C$33:E33)-$B$12 -> 45480.302 | F34: =NPV($B$1,$C$33:F33)-$B$12 -> 68668.783 | G34: =NPV($B$1,$C$33:G33)-$B$12 -> 90246.62 | H34: =NPV($B$1,$C$33:H33)-$B$12 -> 110325.92 | I34: =NPV($B$1,$C$33:I33)-$B$12 -> 129010.97 | J34: =NPV($B$1,$C$33:J33)-$B$12 -> 146398.8 | ... L34: =NPV($B$1,$C$33:L33)-$B$12 -> 177637.5

Sheet Input
A1: Metric | B1: m | C1: m² | D1: m³ | F1: € | H1: 1
A2: Imperial | B2: ft | C2: ft² | D2: ft³ | F2: $ | H2: 2
F3: £ | H3: 3
H4: 4
H5: 5
H6: 6
H7: 7
H8: 8
H9: 9
H10: 10
